[
  {
    "_id": "vul-133001001",
    "version": "vul",
    "chapter": "micah-1",
    "sequence": "133001001",
    "number": 1,
    "text": "verbum Domini quod factum est ad Micham Morasthiten in diebus Ioatham Ahaz Ezechiae regum Iuda quod vidit super Samariam et Hierusalem",
    "paragraphs": [0]
  },
  {
    "_id": "vul-133001002",
    "version": "vul",
    "chapter": "micah-1",
    "sequence": "133001002",
    "number": 2,
    "text": "audite populi omnes et adtendat terra et plenitudo eius et sit Dominus Deus vobis in testem Dominus de templo sancto suo"
  },
  {
    "_id": "vul-133001003",
    "version": "vul",
    "chapter": "micah-1",
    "sequence": "133001003",
    "number": 3,
    "text": "quia ecce Dominus egreditur de loco suo et descendet et calcabit super excelsa terrae"
  },
  {
    "_id": "vul-133001004",
    "version": "vul",
    "chapter": "micah-1",
    "sequence": "133001004",
    "number": 4,
    "text": "et consumentur montes subtus eum et valles scindentur sicut cera a facie ignis sicut aquae quae decurrunt in praeceps"
  },
  {
    "_id": "vul-133001005",
    "version": "vul",
    "chapter": "micah-1",
    "sequence": "133001005",
    "number": 5,
    "text": "in scelere Iacob omne istud et in peccatis domus Israhel quod scelus Iacob nonne Samaria et quae excelsa Iudae nonne Hierusalem"
  },
  {
    "_id": "vul-133001006",
    "version": "vul",
    "chapter": "micah-1",
    "sequence": "133001006",
    "number": 6,
    "text": "et ponam Samariam quasi acervum lapidum in agro cum plantatur vinea et detraham in vallem lapides eius et fundamenta eius revelabo"
  },
  {
    "_id": "vul-133001007",
    "version": "vul",
    "chapter": "micah-1",
    "sequence": "133001007",
    "number": 7,
    "text": "et omnia sculptilia eius concidentur et omnes mercedes eius conburentur igni et omnia idola eius ponam in perditionem quia de mercedibus meretricis congregata sunt et usque ad mercedem meretricis revertentur"
  },
  {
    "_id": "vul-133001008",
    "version": "vul",
    "chapter": "micah-1",
    "sequence": "133001008",
    "number": 8,
    "text": "super hoc plangam et ululabo vadam spoliatus et nudus faciam planctum velut draconum et luctum quasi strutionum"
  },
  {
    "_id": "vul-133001009",
    "version": "vul",
    "chapter": "micah-1",
    "sequence": "133001009",
    "number": 9,
    "text": "quia desperata est plaga eius quia venit usque ad Iudam tetigit portam populi mei usque ad Hierusalem"
  },
  {
    "_id": "vul-133001010",
    "version": "vul",
    "chapter": "micah-1",
    "sequence": "133001010",
    "number": 10,
    "text": "in Geth nolite adnuntiare lacrimis ne ploretis in domo Pulveris pulvere vos conspergite"
  },
  {
    "_id": "vul-133001011",
    "version": "vul",
    "chapter": "micah-1",
    "sequence": "133001011",
    "number": 11,
    "text": "et transite vobis habitatio Pulchra confusa ignominia non est egressa quae habitat in Exitu planctum domus Vicinae accipiet ex vobis quae stetit sibimet"
  },
  {
    "_id": "vul-133001012",
    "version": "vul",
    "chapter": "micah-1",
    "sequence": "133001012",
    "number": 12,
    "text": "quia infirmata est in bonum quae habitat in Amaritudinibus quia descendit malum a Domino in portam Hierusalem"
  },
  {
    "_id": "vul-133001013",
    "version": "vul",
    "chapter": "micah-1",
    "sequence": "133001013",
    "number": 13,
    "text": "tumultus quadrigae stuporis habitanti Lachis principium peccati est filiae Sion quia in te inventa sunt scelera Israhel"
  },
  {
    "_id": "vul-133001014",
    "version": "vul",
    "chapter": "micah-1",
    "sequence": "133001014",
    "number": 14,
    "text": "propterea dabit emissarios super hereditatem Geth domus Mendacii in deceptionem regibus Israhel"
  },
  {
    "_id": "vul-133001015",
    "version": "vul",
    "chapter": "micah-1",
    "sequence": "133001015",
    "number": 15,
    "text": "adhuc heredem adducam tibi quae habitas in Maresa usque Adollam veniet gloria Israhel"
  },
  {
    "_id": "vul-133001016",
    "version": "vul",
    "chapter": "micah-1",
    "sequence": "133001016",
    "number": 16,
    "text": "decalvare et tondere super filios deliciarum tuarum dilata calvitium tuum sicut aquila quoniam captivi ducti sunt ex te"
  },
  {
    "_id": "vul-133002001",
    "version": "vul",
    "chapter": "micah-2",
    "sequence": "133002001",
    "number": 1,
    "text": "vae qui cogitatis inutile et operamini malum in cubilibus vestris in luce matutina faciunt illud quoniam contra Deum est manus eorum",
    "paragraphs": [0]
  },
  {
    "_id": "vul-133002002",
    "version": "vul",
    "chapter": "micah-2",
    "sequence": "133002002",
    "number": 2,
    "text": "et concupierunt agros et violenter tulerunt et domos rapuerunt et calumniabantur virum et domum eius virum et hereditatem eius"
  },
  {
    "_id": "vul-133002003",
    "version": "vul",
    "chapter": "micah-2",
    "sequence": "133002003",
    "number": 3,
    "text": "idcirco haec dicit Dominus ecce ego cogito super familiam istam malum unde non auferetis colla vestra et non ambulabitis superbi quoniam tempus pessimum est"
  },
  {
    "_id": "vul-133002004",
    "version": "vul",
    "chapter": "micah-2",
    "sequence": "133002004",
    "number": 4,
    "text": "in die illa sumetur super vos parabola et cantabitur canticum cum suavitate dicentium depopulatione vastati sumus pars populi mei commutata est quomodo recedet a me cum revertatur qui regiones nostras dividat"
  },
  {
    "_id": "vul-133002005",
    "version": "vul",
    "chapter": "micah-2",
    "sequence": "133002005",
    "number": 5,
    "text": "propter hoc non erit tibi mittens funiculum sortis in coetu Domini"
  },
  {
    "_id": "vul-133002006",
    "version": "vul",
    "chapter": "micah-2",
    "sequence": "133002006",
    "number": 6,
    "text": "ne loquamini loquentes non stillabit super istos non conprehendet confusio"
  },
  {
    "_id": "vul-133002007",
    "version": "vul",
    "chapter": "micah-2",
    "sequence": "133002007",
    "number": 7,
    "text": "dicit domus Iacob numquid adbreviatus est spiritus Domini aut tales sunt cogitationes eius nonne verba mea bona sunt cum eo qui recte graditur"
  },
  {
    "_id": "vul-133002008",
    "version": "vul",
    "chapter": "micah-2",
    "sequence": "133002008",
    "number": 8,
    "text": "et e contrario populus meus in adversarium consurrexit desuper tunica pallium sustulistis eos qui transiebant simpliciter convertistis in bellum"
  },
  {
    "_id": "vul-133002009",
    "version": "vul",
    "chapter": "micah-2",
    "sequence": "133002009",
    "number": 9,
    "text": "mulieres populi mei eiecistis de domo deliciarum suarum a parvulis earum tulistis laudem meam in perpetuum"
  },
  {
    "_id": "vul-133002010",
    "version": "vul",
    "chapter": "micah-2",
    "sequence": "133002010",
    "number": 10,
    "text": "surgite et ite quia non habetis hic requiem propter inmunditiam eius corrumpetur putredine pessima"
  },
  {
    "_id": "vul-133002011",
    "version": "vul",
    "chapter": "micah-2",
    "sequence": "133002011",
    "number": 11,
    "text": "utinam non essem vir habens spiritum et mendacium potius loquerer stillabo tibi in vinum et in ebrietatem et erit super quem stillatur populus iste"
  },
  {
    "_id": "vul-133002012",
    "version": "vul",
    "chapter": "micah-2",
    "sequence": "133002012",
    "number": 12,
    "text": "congregatione congregabo Iacob totum te in unum conducam reliquias Israhel pariter ponam illum quasi gregem in ovili quasi pecus in medio caularum tumultuabuntur a multitudine hominum"
  },
  {
    "_id": "vul-133002013",
    "version": "vul",
    "chapter": "micah-2",
    "sequence": "133002013",
    "number": 13,
    "text": "ascendet enim pandens iter ante eos divident et transibunt portam et egredientur per eam et transibit rex eorum coram eis et Dominus in capite eorum"
  },
  {
    "_id": "vul-133003001",
    "version": "vul",
    "chapter": "micah-3",
    "sequence": "133003001",
    "number": 1,
    "text": "et dixi audite principes Iacob et duces domus Israhel numquid non vestrum est scire iudicium",
    "paragraphs": [0]
  },
  {
    "_id": "vul-133003002",
    "version": "vul",
    "chapter": "micah-3",
    "sequence": "133003002",
    "number": 2,
    "text": "qui odio habetis bonum et diligitis malum qui violenter tollitis pelles eorum desuper eos et carnem eorum desuper ossibus eorum"
  },
  {
    "_id": "vul-133003003",
    "version": "vul",
    "chapter": "micah-3",
    "sequence": "133003003",
    "number": 3,
    "text": "qui comederunt carnem populi mei et pellem eorum desuper excoriaverunt et ossa eorum confregerunt et conciderunt sicut in lebete et quasi carnem in medio ollae"
  },
  {
    "_id": "vul-133003004",
    "version": "vul",
    "chapter": "micah-3",
    "sequence": "133003004",
    "number": 4,
    "text": "tunc clamabunt ad Dominum et non exaudiet eos et abscondet faciem suam ab eis in tempore illo sicut nequiter egerunt in adinventionibus suis"
  },
  {
    "_id": "vul-133003005",
    "version": "vul",
    "chapter": "micah-3",
    "sequence": "133003005",
    "number": 5,
    "text": "haec dicit Dominus super prophetas qui seducunt populum meum qui mordent dentibus suis et praedicant pacem et si quis non dederit in ore eorum quippiam sanctificant super eum proelium"
  },
  {
    "_id": "vul-133003006",
    "version": "vul",
    "chapter": "micah-3",
    "sequence": "133003006",
    "number": 6,
    "text": "propterea nox vobis pro visione erit et tenebrae vobis pro divinatione et occumbet sol super prophetas et obtenebrabitur super eos dies"
  },
  {
    "_id": "vul-133003007",
    "version": "vul",
    "chapter": "micah-3",
    "sequence": "133003007",
    "number": 7,
    "text": "et confundentur qui vident visiones et confundentur divini et operient vultus suos omnes quia non est responsum Dei"
  },
  {
    "_id": "vul-133003008",
    "version": "vul",
    "chapter": "micah-3",
    "sequence": "133003008",
    "number": 8,
    "text": "verumtamen ego repletus sum fortitudine spiritus Domini iudicio et virtute ut adnuntiem Iacob scelus suum et Israhel peccatum suum"
  },
  {
    "_id": "vul-133003009",
    "version": "vul",
    "chapter": "micah-3",
    "sequence": "133003009",
    "number": 9,
    "text": "audite haec principes domus Iacob et iudices domus Israhel qui abominamini iudicium et omnia recta pervertitis"
  },
  {
    "_id": "vul-133003010",
    "version": "vul",
    "chapter": "micah-3",
    "sequence": "133003010",
    "number": 10,
    "text": "qui aedificatis Sion in sanguinibus et Hierusalem in iniquitate"
  },
  {
    "_id": "vul-133003011",
    "version": "vul",
    "chapter": "micah-3",
    "sequence": "133003011",
    "number": 11,
    "text": "principes eius in muneribus iudicabant et sacerdotes eius in mercede docebant et prophetae eius in pecunia divinabant et super Dominum requiescebant dicentes numquid non Dominus in medio nostrum non venient super nos mala"
  },
  {
    "_id": "vul-133003012",
    "version": "vul",
    "chapter": "micah-3",
    "sequence": "133003012",
    "number": 12,
    "text": "propter hoc causa vestri Sion quasi ager arabitur et Hierusalem quasi acervus lapidum erit et mons templi in excelsa silvarum"
  },
  {
    "_id": "vul-133004001",
    "version": "vul",
    "chapter": "micah-4",
    "sequence": "133004001",
    "number": 1,
    "text": "et in novissimo dierum erit mons domus Domini praeparatus in vertice montium et sublimis super colles et fluent ad eum populi",
    "paragraphs": [0]
  },
  {
    "_id": "vul-133004002",
    "version": "vul",
    "chapter": "micah-4",
    "sequence": "133004002",
    "number": 2,
    "text": "et properabunt gentes multae et dicent venite ascendamus ad montem Domini et ad domum Dei Iacob et docebit nos de viis suis et ibimus in semitis eius quia de Sion egredietur lex et verbum Domini de Hierusalem"
  },
  {
    "_id": "vul-133004003",
    "version": "vul",
    "chapter": "micah-4",
    "sequence": "133004003",
    "number": 3,
    "text": "et iudicabit inter populos multos et corripiet gentes fortes usque in longinquum et concident gladios suos in vomeres et hastas suas in ligones non sumet gens adversus gentem gladium et non discent ultra belligerare"
  },
  {
    "_id": "vul-133004004",
    "version": "vul",
    "chapter": "micah-4",
    "sequence": "133004004",
    "number": 4,
    "text": "et sedebit vir subtus vineam suam et subtus ficum suam et non erit qui deterreat quia os Domini exercituum locutum est"
  },
  {
    "_id": "vul-133004005",
    "version": "vul",
    "chapter": "micah-4",
    "sequence": "133004005",
    "number": 5,
    "text": "quia omnes populi ambulabunt unusquisque in nomine dei sui nos autem ambulabimus in nomine Domini Dei nostri in aeternum et ultra"
  },
  {
    "_id": "vul-133004006",
    "version": "vul",
    "chapter": "micah-4",
    "sequence": "133004006",
    "number": 6,
    "text": "in die illa dicit Dominus congregabo claudicantem et eam quam eieceram colligam et quam adflixeram"
  },
  {
    "_id": "vul-133004007",
    "version": "vul",
    "chapter": "micah-4",
    "sequence": "133004007",
    "number": 7,
    "text": "et ponam claudicantem in reliquias et eam quae laboraverat in gentem robustam et regnabit Dominus super eos in monte Sion ex hoc nunc et usque in aeternum"
  },
  {
    "_id": "vul-133004008",
    "version": "vul",
    "chapter": "micah-4",
    "sequence": "133004008",
    "number": 8,
    "text": "et tu turris Gregis nebulosa filiae Sion usque ad te veniet et veniet potestas prima regnum filiae Hierusalem"
  },
  {
    "_id": "vul-133004009",
    "version": "vul",
    "chapter": "micah-4",
    "sequence": "133004009",
    "number": 9,
    "text": "nunc quare maerore contraheris numquid rex non est tibi aut consiliarius tuus periit quia conprehendit te dolor sicut parturientem"
  },
  {
    "_id": "vul-133004010",
    "version": "vul",
    "chapter": "micah-4",
    "sequence": "133004010",
    "number": 10,
    "text": "dole et satage filia Sion quasi parturiens quia nunc egredieris de civitate et habitabis in regione et venies usque ad Babylonem ibi liberaberis ibi redimet te Dominus de manu inimicorum tuorum"
  },
  {
    "_id": "vul-133004011",
    "version": "vul",
    "chapter": "micah-4",
    "sequence": "133004011",
    "number": 11,
    "text": "et nunc congregatae sunt super te gentes multae quae dicunt lapidetur et aspiciat in Sion oculus noster"
  },
  {
    "_id": "vul-133004012",
    "version": "vul",
    "chapter": "micah-4",
    "sequence": "133004012",
    "number": 12,
    "text": "ipsi autem non cognoverunt cogitationes Domini et non intellexerunt consilium eius quia congregavit eos quasi faenum areae"
  },
  {
    "_id": "vul-133004013",
    "version": "vul",
    "chapter": "micah-4",
    "sequence": "133004013",
    "number": 13,
    "text": "surge et tritura filia Sion quia cornu tuum ponam ferreum et ungulas tuas ponam aereas et comminues populos multos et interficiam Domino rapinas eorum et fortitudinem eorum Domino universae terrae"
  },
  {
    "_id": "vul-133005001",
    "version": "vul",
    "chapter": "micah-5",
    "sequence": "133005001",
    "number": 1,
    "text": "nunc vastaberis filia latronis obsidionem posuerunt super nos in virga percutient maxillam iudicis Israhel",
    "paragraphs": [0]
  },
  {
    "_id": "vul-133005002",
    "version": "vul",
    "chapter": "micah-5",
    "sequence": "133005002",
    "number": 2,
    "text": "et tu Bethleem Ephrata parvulus es in milibus Iuda ex te mihi egredietur qui sit dominator in Israhel et egressus eius ab initio a diebus aeternitatis"
  },
  {
    "_id": "vul-133005003",
    "version": "vul",
    "chapter": "micah-5",
    "sequence": "133005003",
    "number": 3,
    "text": "propter hoc dabit eos usque ad tempus in quo parturiens pariet reliquiae fratrum eius convertentur ad filios Israhel"
  },
  {
    "_id": "vul-133005004",
    "version": "vul",
    "chapter": "micah-5",
    "sequence": "133005004",
    "number": 4,
    "text": "et stabit et pascet in fortitudine Domini in sublimitate nominis Domini Dei sui et convertentur quia nunc magnificabitur usque ad terminos terrae"
  },
  {
    "_id": "vul-133005005",
    "version": "vul",
    "chapter": "micah-5",
    "sequence": "133005005",
    "number": 5,
    "text": "et erit iste pax Assyrius cum venerit in terram nostram et quando calcaverit in domibus nostris et suscitabimus super eum septem pastores et octo primates homines"
  },
  {
    "_id": "vul-133005006",
    "version": "vul",
    "chapter": "micah-5",
    "sequence": "133005006",
    "number": 6,
    "text": "et pascent terram Assur in gladio et terram Nemrod in lanceis eius et liberabit ab Assur cum venerit in terram nostram et cum calcaverit in finibus nostris"
  },
  {
    "_id": "vul-133005007",
    "version": "vul",
    "chapter": "micah-5",
    "sequence": "133005007",
    "number": 7,
    "text": "et erunt reliquiae Iacob in medio populorum multorum quasi ros a Domino et quasi stillae super herbam quae non expectat virum et non praestolatur filios hominum"
  },
  {
    "_id": "vul-133005008",
    "version": "vul",
    "chapter": "micah-5",
    "sequence": "133005008",
    "number": 8,
    "text": "et erunt reliquiae Iacob in gentibus in medio populorum multorum quasi leo in iumentis silvarum et quasi catulus leonis in gregibus pecorum qui cum transierit et conculcaverit et ceperit non est qui eruat"
  },
  {
    "_id": "vul-133005009",
    "version": "vul",
    "chapter": "micah-5",
    "sequence": "133005009",
    "number": 9,
    "text": "exaltabitur manus tua super hostes tuos et omnes inimici tui interibunt"
  },
  {
    "_id": "vul-133005010",
    "version": "vul",
    "chapter": "micah-5",
    "sequence": "133005010",
    "number": 10,
    "text": "et erit in die illa dicit Dominus auferam equos tuos de medio tui et disperdam quadrigas tuas"
  },
  {
    "_id": "vul-133005011",
    "version": "vul",
    "chapter": "micah-5",
    "sequence": "133005011",
    "number": 11,
    "text": "et perdam civitates terrae tuae et destruam omnes munitiones tuas"
  },
  {
    "_id": "vul-133005012",
    "version": "vul",
    "chapter": "micah-5",
    "sequence": "133005012",
    "number": 12,
    "text": "(5-11) et auferam maleficia de manu tua et divinationes non erunt in te"
  },
  {
    "_id": "vul-133005013",
    "version": "vul",
    "chapter": "micah-5",
    "sequence": "133005013",
    "number": 13,
    "text": "(5-12) et perire faciam sculptilia tua et statuas tuas de medio tui et non adorabis ultra opera manuum tuarum"
  },
  {
    "_id": "vul-133005014",
    "version": "vul",
    "chapter": "micah-5",
    "sequence": "133005014",
    "number": 14,
    "text": "(5-13) et evellam lucos tuos de medio tui et conteram civitates tuas"
  },
  {
    "_id": "vul-133005015",
    "version": "vul",
    "chapter": "micah-5",
    "sequence": "133005015",
    "number": 15,
    "text": "(5-14) et faciam in furore et in indignatione ultionem in omnibus gentibus quae non audierunt"
  },
  {
    "_id": "vul-133006001",
    "version": "vul",
    "chapter": "micah-6",
    "sequence": "133006001",
    "number": 1,
    "text": "audite quae Dominus loquitur surge contende iudicio adversum montes et audiant colles vocem tuam",
    "paragraphs": [0]
  },
  {
    "_id": "vul-133006002",
    "version": "vul",
    "chapter": "micah-6",
    "sequence": "133006002",
    "number": 2,
    "text": "audiant montes iudicium Domini et fortia fundamenta terrae quia iudicium Domini cum populo suo et cum Israhel diiudicabitur"
  },
  {
    "_id": "vul-133006003",
    "version": "vul",
    "chapter": "micah-6",
    "sequence": "133006003",
    "number": 3,
    "text": "populus meus quid feci tibi et quid molestus fui tibi responde mihi"
  },
  {
    "_id": "vul-133006004",
    "version": "vul",
    "chapter": "micah-6",
    "sequence": "133006004",
    "number": 4,
    "text": "quia eduxi te de terra Aegypti et de domo servientium liberavi te et misi ante faciem tuam Mosen et Aaron et Mariam"
  },
  {
    "_id": "vul-133006005",
    "version": "vul",
    "chapter": "micah-6",
    "sequence": "133006005",
    "number": 5,
    "text": "populus meus memento quaeso quid cogitaverit Balac rex Moab et quid responderit ei Balaam filius Beor de Setthim usque ad Galgalam ut cognosceret iustitias Domini"
  },
  {
    "_id": "vul-133006006",
    "version": "vul",
    "chapter": "micah-6",
    "sequence": "133006006",
    "number": 6,
    "text": "quid dignum offeram Domino curvem genu Deo excelso numquid offeram ei holocaustomata et vitulos anniculos"
  },
  {
    "_id": "vul-133006007",
    "version": "vul",
    "chapter": "micah-6",
    "sequence": "133006007",
    "number": 7,
    "text": "numquid placari potest Dominus in milibus arietum aut in multis milibus hircorum pinguium numquid dabo primogenitum meum pro scelere meo fructum ventris mei pro peccato animae meae"
  },
  {
    "_id": "vul-133006008",
    "version": "vul",
    "chapter": "micah-6",
    "sequence": "133006008",
    "number": 8,
    "text": "indicabo tibi o homo quid sit bonum et quid Dominus quaerat a te utique facere iudicium et diligere misericordiam et sollicitum ambulare cum Deo tuo"
  },
  {
    "_id": "vul-133006009",
    "version": "vul",
    "chapter": "micah-6",
    "sequence": "133006009",
    "number": 9,
    "text": "vox Domini ad civitatem clamat et salus erit timentibus nomen tuum audite tribus et quis adprobabit illud"
  },
  {
    "_id": "vul-133006010",
    "version": "vul",
    "chapter": "micah-6",
    "sequence": "133006010",
    "number": 10,
    "text": "adhuc ignis in domo impii thesauri iniquitatis et mensura minor irae plena"
  },
  {
    "_id": "vul-133006011",
    "version": "vul",
    "chapter": "micah-6",
    "sequence": "133006011",
    "number": 11,
    "text": "numquid iustificabo stateram impiam et saccelli pondera dolosa"
  },
  {
    "_id": "vul-133006012",
    "version": "vul",
    "chapter": "micah-6",
    "sequence": "133006012",
    "number": 12,
    "text": "in quibus divites eius repleti sunt iniquitate et habitantes in ea loquebantur mendacium et lingua eorum fraudulenta in ore eorum"
  },
  {
    "_id": "vul-133006013",
    "version": "vul",
    "chapter": "micah-6",
    "sequence": "133006013",
    "number": 13,
    "text": "et ego ergo coepi percutere te perditione super peccatis tuis"
  },
  {
    "_id": "vul-133006014",
    "version": "vul",
    "chapter": "micah-6",
    "sequence": "133006014",
    "number": 14,
    "text": "tu comedes et non saturaberis et humiliatio tua in medio tui et adprehendes et non salvabis et quos salvaveris in gladium dabo"
  },
  {
    "_id": "vul-133006015",
    "version": "vul",
    "chapter": "micah-6",
    "sequence": "133006015",
    "number": 15,
    "text": "tu seminabis et non metes tu calcabis olivam et non ungueris oleo et mustum et non bibes vinum"
  },
  {
    "_id": "vul-133006016",
    "version": "vul",
    "chapter": "micah-6",
    "sequence": "133006016",
    "number": 16,
    "text": "et custodisti praecepta Omri et omne opus domus Achab et ambulasti in voluntatibus eorum ut darem te in perditionem et habitantes in ea in sibilum et obprobrium populi mei portabitis"
  },
  {
    "_id": "vul-133007001",
    "version": "vul",
    "chapter": "micah-7",
    "sequence": "133007001",
    "number": 1,
    "text": "vae mihi quia factus sum sicut qui colligit in autumno racemos vindemiae non est botrus ad comedendum praecoquas ficus desideravit anima mea",
    "paragraphs": [0]
  },
  {
    "_id": "vul-133007002",
    "version": "vul",
    "chapter": "micah-7",
    "sequence": "133007002",
    "number": 2,
    "text": "periit sanctus de terra et rectus in hominibus non est omnes in sanguine insidiantur vir fratrem suum venatur ad mortem"
  },
  {
    "_id": "vul-133007003",
    "version": "vul",
    "chapter": "micah-7",
    "sequence": "133007003",
    "number": 3,
    "text": "malum manuum suarum dicunt bonum princeps postulat et iudex in reddendo est et magnus locutus est desiderium animae suae et conturbaverunt eam"
  },
  {
    "_id": "vul-133007004",
    "version": "vul",
    "chapter": "micah-7",
    "sequence": "133007004",
    "number": 4,
    "text": "qui optimus in eis est quasi paliurus et qui rectus quasi spina de sepe dies speculationis tuae visitatio tua venit nunc erit vastitas eorum"
  },
  {
    "_id": "vul-133007005",
    "version": "vul",
    "chapter": "micah-7",
    "sequence": "133007005",
    "number": 5,
    "text": "nolite credere amico et nolite confidere in duce ab ea quae dormit in sinu tuo custodi claustra oris tui"
  },
  {
    "_id": "vul-133007006",
    "version": "vul",
    "chapter": "micah-7",
    "sequence": "133007006",
    "number": 6,
    "text": "quia filius contumeliam facit patri filia consurgit adversus matrem suam nurus contra socrum suam inimici hominis domestici eius"
  },
  {
    "_id": "vul-133007007",
    "version": "vul",
    "chapter": "micah-7",
    "sequence": "133007007",
    "number": 7,
    "text": "ego autem ad Dominum aspiciam expectabo Deum salvatorem meum audiet me Deus meus"
  },
  {
    "_id": "vul-133007008",
    "version": "vul",
    "chapter": "micah-7",
    "sequence": "133007008",
    "number": 8,
    "text": "ne laeteris inimica mea super me quia cecidi consurgam cum sedero in tenebris Dominus lux mea est"
  },
  {
    "_id": "vul-133007009",
    "version": "vul",
    "chapter": "micah-7",
    "sequence": "133007009",
    "number": 9,
    "text": "iram Domini portabo quoniam peccavi ei donec iudicet causam meam et faciat iudicium meum educet me in lucem videbo in iustitiam eius"
  },
  {
    "_id": "vul-133007010",
    "version": "vul",
    "chapter": "micah-7",
    "sequence": "133007010",
    "number": 10,
    "text": "et aspiciet inimica mea et operietur confusione quae dicit ad me ubi est Dominus Deus tuus oculi mei videbunt in eam nunc erit in conculcationem ut lutum platearum"
  },
  {
    "_id": "vul-133007011",
    "version": "vul",
    "chapter": "micah-7",
    "sequence": "133007011",
    "number": 11,
    "text": "dies ut aedificentur maceriae tuae in die illa longe fiet lex"
  },
  {
    "_id": "vul-133007012",
    "version": "vul",
    "chapter": "micah-7",
    "sequence": "133007012",
    "number": 12,
    "text": "in die illa et usque ad te veniet Assur et usque ad civitates munitas et a civitatibus munitis usque ad flumen et ad mare de mari et ad montem de monte"
  },
  {
    "_id": "vul-133007013",
    "version": "vul",
    "chapter": "micah-7",
    "sequence": "133007013",
    "number": 13,
    "text": "et erit terra in desolationem propter habitatores suos et propter fructum cogitationum eorum"
  },
  {
    "_id": "vul-133007014",
    "version": "vul",
    "chapter": "micah-7",
    "sequence": "133007014",
    "number": 14,
    "text": "pasce populum tuum in virga tua gregem hereditatis tuae habitantes solos in saltu in medio Carmeli pascentur Basan et Galaad iuxta dies antiquos"
  },
  {
    "_id": "vul-133007015",
    "version": "vul",
    "chapter": "micah-7",
    "sequence": "133007015",
    "number": 15,
    "text": "secundum dies egressionis tuae de terra Aegypti ostendam ei mirabilia"
  },
  {
    "_id": "vul-133007016",
    "version": "vul",
    "chapter": "micah-7",
    "sequence": "133007016",
    "number": 16,
    "text": "videbunt gentes et confundentur super omni fortitudine sua ponent manus super os aures eorum surdae erunt"
  },
  {
    "_id": "vul-133007017",
    "version": "vul",
    "chapter": "micah-7",
    "sequence": "133007017",
    "number": 17,
    "text": "lingent pulverem sicut serpens velut reptilia terrae proturbabuntur de aedibus suis Dominum Deum nostrum desiderabunt et timebunt te"
  },
  {
    "_id": "vul-133007018",
    "version": "vul",
    "chapter": "micah-7",
    "sequence": "133007018",
    "number": 18,
    "text": "quis Deus similis tui qui aufers iniquitatem et transis peccatum reliquiarum hereditatis tuae non inmittet ultra furorem suum quoniam volens misericordiam est"
  },
  {
    "_id": "vul-133007019",
    "version": "vul",
    "chapter": "micah-7",
    "sequence": "133007019",
    "number": 19,
    "text": "revertetur et miserebitur nostri deponet iniquitates nostras et proiciet in profundum maris omnia peccata nostra"
  },
  {
    "_id": "vul-133007020",
    "version": "vul",
    "chapter": "micah-7",
    "sequence": "133007020",
    "number": 20,
    "text": "dabis veritatem Iacob misericordiam Abraham quae iurasti patribus nostris a diebus antiquis"
  }
]
